remote_ipykernel/__init__.py
remote_ipykernel/__main__.py
remote_ipykernel/__version.py
remote_ipykernel/compat.py
remote_ipykernel/kernel.py
remote_ipykernel/manage.py
remote_ipykernel-1.0.2.dist-info/LICENSE.txt
remote_ipykernel-1.0.2.dist-info/METADATA
remote_ipykernel-1.0.2.dist-info/WHEEL
remote_ipykernel-1.0.2.dist-info/entry_points.txt
remote_ipykernel-1.0.2.dist-info/top_level.txt
remote_ipykernel-1.0.2.dist-info/RECORD
