Metadata-Version: 2.1
Name: remote-ipykernel
Version: 1.0.2
Summary: Running IPython kernels remotely and through batch queues
Author: Tom Daff, Conor Wills
License: BSD
Project-URL: Homepage, https://github.com/CWills96/remote_ipykernel
Classifier: Programming Language :: Python :: 3
Classifier: Framework :: IPython
Classifier: License :: OSI Approved :: BSD License
Requires-Python: >=3.7
License-File: LICENSE.txt
Requires-Dist: notebook (>=6)
Requires-Dist: pexpect (>=4)
Requires-Dist: tornado (>=4)
